functional_predicates/__init__.py
functional_predicates/base.py
functional_predicates/check.py
functional_predicates/errors.py
functional_predicates/misc.py
functional_predicates/predicates/__init__.py
functional_predicates/predicates/builtin.py
functional_predicates/predicates/operator.py
functional_predicates/predicates/predicate.py
tests/predicates/__init__.py
tests/predicates/test_builtin.py
tests/predicates/test_operator.py
functional_predicates-0.1.9.dist-info/METADATA
functional_predicates-0.1.9.dist-info/WHEEL
functional_predicates-0.1.9.dist-info/top_level.txt
functional_predicates-0.1.9.dist-info/RECORD
