Metadata-Version: 2.1
Name: functional-predicates
Version: 0.1.9
Summary: Python predicates in a functional-programming style
Home-page: UNKNOWN
Author: Bao Wei
Author-email: baowei.ur521@gmail.com
License: MIT
Platform: UNKNOWN
Requires-Python: >=3.7
Requires-Dist: colored (>=1.4)
